{"id":"openreview:wFLc5L23QL;icml:60831","type":"paper","title":"GuidedBridge: Training-freely Improving Bridge Models with Prior Guidance","category":"Other","areaTags":["Vision","Generative Models"],"domainTags":["Biology","Scientific Discovery"],"referenceCount":1,"referenceKeys":["eds computer vision eccv"],"references":[{"key":"eds computer vision eccv","raw":"Varol, G. (eds.), Computer Vision – ECCV 2024, 2025. In this work, we propose PG and its extension FMPG, two training-free guidance methods tailored for diffusion bridge Anonymous. Dynamic classifier-free diffusion guida","title":"(eds.), Computer Vision – ECCV 2024, 2025","authors":[]}],"overlaps":[]}